./.gitignore
./CLAUDE.md
./Dockerfile
./LICENSE
./PKG-INFO
./README.md
./language.json
./package_name
./push_info.json
./pyproject.toml
./requirements.txt
./server.py
./server_config.json
./server_main.py
./smithery.yaml
iflow_mcp_buuzzy_tushare_mcp-0.1.2.dist-info/METADATA
iflow_mcp_buuzzy_tushare_mcp-0.1.2.dist-info/WHEEL
iflow_mcp_buuzzy_tushare_mcp-0.1.2.dist-info/entry_points.txt
iflow_mcp_buuzzy_tushare_mcp-0.1.2.dist-info/licenses/LICENSE
iflow_mcp_buuzzy_tushare_mcp-0.1.2.dist-info/RECORD
