Metadata-Version: 2.4
Name: iflow-mcp-buuzzy-tushare_mcp
Version: 0.1.2
Summary: A股数据查询服务，基于 MCP (Model Context Protocol) 协议，支持通过 AI 助手用自然语言查询股票数据
License-File: LICENSE
Requires-Python: >=3.8
Requires-Dist: annotated-types>=0.7.0
Requires-Dist: anyio>=4.9.0
Requires-Dist: beautifulsoup4>=4.13.4
Requires-Dist: bs4>=0.0.2
Requires-Dist: certifi>=2025.4.26
Requires-Dist: charset-normalizer>=3.4.2
Requires-Dist: click>=8.1.8
Requires-Dist: fastapi>=0.115.12
Requires-Dist: h11>=0.16.0
Requires-Dist: httpcore>=1.0.9
Requires-Dist: httptools>=0.6.4
Requires-Dist: httpx-sse>=0.4.0
Requires-Dist: httpx>=0.28.1
Requires-Dist: idna>=3.10
Requires-Dist: lxml>=5.4.0
Requires-Dist: mcp>=1.7.1
Requires-Dist: numpy>=2.2.5
Requires-Dist: pandas>=2.2.3
Requires-Dist: pydantic-core>=2.33.2
Requires-Dist: pydantic-settings>=2.9.1
Requires-Dist: pydantic>=2.11.4
Requires-Dist: python-dateutil>=2.9.0.post0
Requires-Dist: python-dotenv>=1.1.0
Requires-Dist: python-multipart>=0.0.20
Requires-Dist: pytz>=2025.2
Requires-Dist: pyyaml>=6.0.2
Requires-Dist: requests>=2.32.3
Requires-Dist: simplejson>=3.20.1
Requires-Dist: six>=1.17.0
Requires-Dist: sniffio>=1.3.1
Requires-Dist: soupsieve>=2.7
Requires-Dist: sse-starlette>=2.3.4
Requires-Dist: starlette>=0.46.2
Requires-Dist: tinyshare
Requires-Dist: tqdm>=4.67.1
Requires-Dist: tushare>=1.4.21
Requires-Dist: typing-extensions>=4.13.2
Requires-Dist: typing-inspection>=0.4.0
Requires-Dist: tzdata>=2025.2
Requires-Dist: urllib3>=2.4.0
Requires-Dist: uvicorn>=0.34.2
Requires-Dist: uvloop>=0.21.0
Requires-Dist: watchfiles>=1.0.5
Requires-Dist: websocket-client>=1.8.0
Requires-Dist: websockets>=15.0.1
